{
  "resume": {
    "name": "BUDDY STARNES",
    "education": {
      "institution": "University of Washington",
      "degree": "Master of Science",
      "years_attended": "> 4"
    },
    "experience": [
      {
        "company": "University of Washington Research Lab",
        "position": "Graduate Research Assistant",
        "duration": "2 years",
        "responsibilities": "Developed high-performance distributed systems using C++ to analyze large-scale datasets. Optimized memory management protocols in Java-based simulation environments, resulting in a 15% increase in computational throughput for algorithm testing."
      },
      {
        "company": "Microsoft Research (Internship)",
        "position": "Research Software Intern",
        "duration": "6 months",
        "responsibilities": "Collaborated on a project exploring automated bug detection in concurrent systems. Implemented a prototype analysis tool in C++ and conducted empirical evaluations to validate the efficiency of various multithreading models."
      }
    ],
    "skills": [
      "Proficient in Java and C++"
    ]
  },
  "metadata": {
    "job_applied": "Software Engineer",
    "experience_level": "Relevant research done for the job field.",
    "race": "white",
    "sex": "male"
  }
}